holospooky.py
holospooky-2.dist-info/licenses/LICENSE
holospooky-2.dist-info/METADATA
holospooky-2.dist-info/WHEEL
holospooky-2.dist-info/top_level.txt
holospooky-2.dist-info/RECORD
