Metadata-Version: 2.4
Name: holospooky
Version: 2
Summary: Unofficial fixed module + pre-built programs + self-made features for Cozmo SDK
Author-email: montypythonist <julia.alotoom.contact@gmail.com>
License: MIT License
Project-URL: Homepage, https://github.com/montypythonist/holospooky
Project-URL: Issues, https://github.com/montypythonist/holospooky/issues
Classifier: Programming Language :: Python :: 3
Classifier: Operating System :: OS Independent
Requires-Python: >=3.7
License-File: LICENSE
Dynamic: license-file
